deploy_ostree/__init__.py
deploy_ostree/__main__.py
deploy_ostree/clsutil.py
deploy_ostree/config_source.py
deploy_ostree/run.py
deploy_ostree/builtin-provisioners/authorized-keys
deploy_ostree/builtin-provisioners/create-user
deploy_ostree/builtin-provisioners/etc-fstab
deploy_ostree/builtin-provisioners/etc-network-interfaces
deploy_ostree/builtin-provisioners/passwordless-sudo
deploy_ostree/builtin-provisioners/root-password
deploy_ostree/config/__init__.py
deploy_ostree/config/error.py
deploy_ostree/config/provisioners.py
deploy_ostree/config/rootfs.py
deploy_ostree/steps/__init__.py
deploy_ostree/steps/create_stateroot.py
deploy_ostree/steps/delete_remote.py
deploy_ostree/steps/deploy.py
deploy_ostree/steps/deploystep.py
deploy_ostree/steps/fstab.py
deploy_ostree/steps/mount_var.py
deploy_ostree/steps/pull_ref.py
deploy_ostree/steps/remote.py
deploy_ostree/steps/provisioners/__init__.py
deploy_ostree/steps/provisioners/script.py
deploy_ostree/steps/provisioners/builtin/__init__.py
deploy_ostree/steps/provisioners/builtin/machine_id.py
deploy_ostree/steps/provisioners/builtin/shell.py
deploy_ostree-1.3.0.dist-info/LICENSE
deploy_ostree-1.3.0.dist-info/METADATA
deploy_ostree-1.3.0.dist-info/WHEEL
deploy_ostree-1.3.0.dist-info/entry_points.txt
deploy_ostree-1.3.0.dist-info/top_level.txt
deploy_ostree-1.3.0.dist-info/RECORD
