Metadata-Version: 2.1
Name: deploy-ostree
Version: 1.3.0
Summary: Deploy and configure an OSTree commit
Home-page: https://gitlab.com/fkrull/deploy-ostree
Author: Felix Krull
Author-email: f_krull@gmx.de
License: UNKNOWN
Platform: UNKNOWN
Classifier: Development Status :: 5 - Production/Stable
Classifier: Intended Audience :: Developers
Classifier: Environment :: Console
Classifier: Topic :: System :: Boot
Classifier: Topic :: System :: Operating System
Classifier: Operating System :: POSIX :: Linux
Classifier: License :: OSI Approved :: MIT License
Classifier: Programming Language :: Python :: 3
Classifier: Programming Language :: Python :: 3.5
Classifier: Programming Language :: Python :: 3.6
Classifier: Programming Language :: Python :: 3.7
Requires-Dist: toml (>=0.10)
Provides-Extra: dev
Requires-Dist: flake8 ; extra == 'dev'
Requires-Dist: mypy ; extra == 'dev'
Requires-Dist: pytest ; extra == 'dev'
Requires-Dist: twine (>=1.12) ; extra == 'dev'
Requires-Dist: readme-renderer[md] ; extra == 'dev'
Provides-Extra: test
Requires-Dist: pytest ; extra == 'test'
